[
  {
    "q": "인공지능은 인간의 지적 능력(인식·학습·추론·문제 해결 등)의 일부 또는 전체를 컴퓨팅 시스템으로 구현한 것이다.",
    "a": "O",
    "exp": "교과서에서는 인공지능을 ‘인공적인 지능’으로 정의하며, 인간의 지적 능력을 컴퓨팅으로 구현한다고 설명합니다."
  },
  {
    "q": "교과서에서 말하는 ‘지능’은 새로운 대상이나 상황의 의미를 이해하고, 합리적인 적응 방법을 알아내는 지적 활동 능력이다.",
    "a": "O",
    "exp": "‘지능’은 상황의 의미를 이해하고 적응 방법을 찾는 능력으로 정리됩니다."
  },
  {
    "q": "오늘날 인공지능은 실생활에서만 사용되며, 연구 분야에는 거의 활용되지 않는다.",
    "a": "X",
    "exp": "실생활뿐 아니라 다양한 학문 분야의 연구에도 활용된다고 설명됩니다."
  },
  {
    "q": "생성형 인공지능 기반 챗봇은 질문 내용을 이해하고 적절한 대답을 제공하는 사례로 소개된다.",
    "a": "O",
    "exp": "교과서의 예시에서 챗봇이 질문을 이해하고 대답을 제공하는 장면이 제시됩니다."
  },
  {
    "q": "자율 주행 자동차는 주변 상황과 차량을 인식해 목적지까지 안전하게 주행할 수 있다.",
    "a": "O",
    "exp": "교과서 예시에서 교통 상황과 주변 차량을 인식해 안전하게 주행한다고 설명합니다."
  }
]